batre/__init__.py
batre/aggregate.py
batre/export-working-dry.py
batre/export.py
batre/samplebase.py
batre/sync.py
batre/utils.py
batre/vcs/base_strategy.py
batre/vcs/bitbucket_strategy.py
batre/vcs/github_strategy.py
batre/vcs/gitlab_strategy.py
batre_translator_cli-0.1.1.dist-info/METADATA
batre_translator_cli-0.1.1.dist-info/WHEEL
batre_translator_cli-0.1.1.dist-info/entry_points.txt
batre_translator_cli-0.1.1.dist-info/top_level.txt
batre_translator_cli-0.1.1.dist-info/RECORD
